Metadata-Version: 2.1
Name: inspire-crawler
Version: 3.0.4
Summary: Crawler integration with INSPIRE-HEP.
Home-page: https://github.com/inspirehep/inspire-crawler
Author: CERN
Author-email: feedback@inspirehep.net
License: GPLv2
Keywords: invenio inspire scrapy crawler
Platform: any
Classifier: Environment :: Web Environment
Classifier: Intended Audience :: Developers
Classifier: License :: OSI Approved :: GNU General Public License v2 (GPLv2)
Classifier: Operating System :: OS Independent
Classifier: Programming Language :: Python
Classifier: Topic :: Internet :: WWW/HTTP :: Dynamic Content
Classifier: Topic :: Software Development :: Libraries :: Python Modules
Classifier: Programming Language :: Python :: 2
Classifier: Programming Language :: Python :: 2.7
Classifier: Programming Language :: Python :: 3
Classifier: Programming Language :: Python :: 3.3
Classifier: Programming Language :: Python :: 3.4
Classifier: Programming Language :: Python :: 3.5
Classifier: Development Status :: 1 - Planning
Provides-Extra: sqlite
Provides-Extra: postgresql
Provides-Extra: docs
Provides-Extra: all
Provides-Extra: tests
Provides-Extra: mysql
